orca_core/__init__.py
orca_core/api/__init__.py
orca_core/api/api.py
orca_core/core.py
orca_core/hardware/__init__.py
orca_core/hardware/dynamixel_client.py
orca_core/hardware/mock_dynamixel_client.py
orca_core/models/orcahand_v1_right/calibration.yaml
orca_core/models/orcahand_v1_right/config.yaml
orca_core/utils/__init__.py
orca_core/utils/load_utils.py
orca_core/utils/yaml_utils.py
orca_core-1.0.0.dist-info/LICENSE
orca_core-1.0.0.dist-info/METADATA
orca_core-1.0.0.dist-info/WHEEL
orca_core-1.0.0.dist-info/RECORD
