Metadata-Version: 2.3
Name: orca_core
Version: 1.0.0
Summary: Core Python Controller of the ORCA Hand. Handles all hardware interaction, logic and abstracts control. Provides API for basic functionality and info of the hand.
License: MIT
Author: clemens-chr
Author-email: cchristoph@student.ethz.ch
Requires-Python: >=3.10
Classifier: License :: OSI Approved :: MIT License
Classifier: Programming Language :: Python :: 3
Classifier: Programming Language :: Python :: 3.10
Classifier: Programming Language :: Python :: 3.11
Classifier: Programming Language :: Python :: 3.12
Classifier: Programming Language :: Python :: 3.13
Requires-Dist: dynamixel-sdk (>=3.7.31,<4.0.0)
Requires-Dist: fastapi (>=0.115.12,<0.116.0)
Requires-Dist: httpx (>=0.28.1,<0.29.0)
Requires-Dist: numpy (>=2.2.6,<3.0.0)
Requires-Dist: pytest (>=8.3.5,<9.0.0)
Requires-Dist: pyyaml (>=6.0.2,<7.0.0)
Requires-Dist: requests (>=2.32.3,<3.0.0)
Requires-Dist: uvicorn (>=0.34.2,<0.35.0)
